{"aka": "Southern Light", "asn": 13760, "created": "2016-05-26 12:04:17.667608", "id": "6485", "info_ipv6": 1, "info_multicast": 0, "info_prefixes4": 75, "info_prefixes6": 4, "info_ratio": "Mostly Inbound", "info_scope": "Regional", "info_traffic": "20-50 Gbps", "info_type": "transit", "info_unicast": 1, "irr_as_set": "", "looking_glass": "", "name": "Southern Light, LLC", "notes": "", "notes_private": "", "org_id": 8930, "policy_contracts": "Not Required", "policy_general": "Open", "policy_locations": "Not Required", "policy_ratio": 0, "policy_url": "", "route_server": "", "status": "ok", "updated": "2016-05-26 12:04:17.667628", "version": 0, "website": "http://www.southernlightfiber.com", "pop_list": [{"city": "Jacksonville", "country": "US", "state": "FL", "org_name": "421 West Church Street", "isp_id_in_peering_db": 563, "location": [33.78, -84.29], "port_capacity": 1000, "isp_type_in_peering_db": "fac", "internet_penetration_percentage": 0.8420000000000001}, {"city": "Atlanta", "country": "US", "state": "GA", "org_name": "Telx", "isp_id_in_peering_db": 125, "location": [33.76, -84.39], "port_capacity": 11000, "isp_type_in_peering_db": "fac", "internet_penetration_percentage": 0.847}, {"city": "Miami", "country": "US", "state": "FL", "org_name": "Verizon", "isp_id_in_peering_db": 15, "location": [25.78, -80.19], "port_capacity": 1000, "isp_type_in_peering_db": "fac", "internet_penetration_percentage": 0.8420000000000001}, {"city": "Dallas", "country": "US", "state": "TX", "org_name": "Equinix", "isp_id_in_peering_db": 69, "location": [32.8, -96.82], "port_capacity": 11000, "isp_type_in_peering_db": "fac", "internet_penetration_percentage": 0.8170000000000001}], "prefixes": 4197, "total_prefixes_in_globe": 8388478, "address_space": 13720944, "total_addresses_in_globe": 22264797636, "neighbor": 132}