{"aka": "", "asn": 812, "created": "2016-05-26 12:02:34.634146", "id": "307", "info_ipv6": 1, "info_multicast": 0, "info_prefixes4": 2000, "info_prefixes6": 100, "info_ratio": "Mostly Inbound", "info_scope": "Regional", "info_traffic": "100-200 Gbps", "info_type": "access", "info_unicast": 1, "irr_as_set": "AS-ROGERS", "looking_glass": "http://lg.rogers.com", "name": "Rogers Cable", "notes": "", "notes_private": "", "org_id": 423, "policy_contracts": "Required", "policy_general": "Selective", "policy_locations": "Preferred", "policy_ratio": 0, "policy_url": "", "route_server": "telnet://route-server.rogers.com", "status": "ok", "updated": "2016-05-26 12:02:34.634166", "version": 0, "website": "http://www.rogers.com", "pop_list": [{"city": "Ashburn", "country": "US", "state": "VA", "org_name": "Equinix", "isp_id_in_peering_db": 1, "location": [39.02, -77.46], "port_capacity": 11000, "isp_type_in_peering_db": "fac", "internet_penetration_percentage": 0.852}, {"city": "Chicago", "country": "US", "state": "IL", "org_name": "Equinix", "isp_id_in_peering_db": 7, "location": [41.85, -87.62], "port_capacity": 21000, "isp_type_in_peering_db": "fac", "internet_penetration_percentage": 0.865}, {"city": "New York", "country": "US", "state": "NY", "org_name": "Equinix", "isp_id_in_peering_db": 12, "location": [40.74, -74.0], "port_capacity": 21000, "isp_type_in_peering_db": "ix", "internet_penetration_percentage": 0.802}, {"city": "Seattle", "country": "US", "state": "WA", "org_name": "The Westin Building", "isp_id_in_peering_db": 71, "location": [47.61, -122.34], "port_capacity": 2000, "isp_type_in_peering_db": "fac", "internet_penetration_percentage": 0.885}], "prefixes": 2518, "total_prefixes_in_globe": 8388478, "address_space": 7750912, "total_addresses_in_globe": 22264797636, "neighbor": 190}