{"status": "ok", "looking_glass": "", "route_server": "", "netixlan_updated": "2021-03-04T12:24:57.133083Z", "info_ratio": "Balanced", "id": "1418", "policy_ratio": false, "info_unicast": true, "policy_general": "Selective", "website": "http://www.amazon.com", "allow_ixp_update": false, "updated": "2021-02-11T02:31:58Z", "netfac_updated": "2021-02-01T17:11:27Z", "info_traffic": "", "info_multicast": false, "asn": 16509, "policy_locations": "Preferred", "name": "Amazon.com", "info_scope": "Global", "notes": "Peering requests:\n\nWhen requesting submitting a peering request, please address the specific regional contact listed below for the location of your request (i.e. peering requests for London should use peering-emea@amazon.com while peering requests for Singapore should use peering-apac@amazon.com). This will ensure your request is processed and addressed in a timely fashion. Please do not copy contacts not meant for peering policy in the location of your request.\n\n-----\n\nOperational issues:\n\nIf you experience connectivity issues to Amazon, please first visit: http://ec2-reachability.amazonaws.com/.\nWhen contacting our Operational alias below, please include trace/debug information (source and destination address) and details for the affected prefixes. This will reduce troubleshooting time.\n\nAustralia - We are no longer peering on PIPE or MegaIX. \nSingapore - no longer peering on MegaIX.\nPlease email peering-apac@amazon.com to establish alternative peering.\n\n----\n\nInformational:\n\nFor details about our network, routing and interconnection options, please see https://peering.aws.\nA list of our IP ranges with source location information is maintained here: https://ip-ranges.amazonaws.com/ip-ranges.json.\nPlease use the Maintenance alias to notify us regarding maintenance activities on your end and do not copy other aliases into these inquiries.  \n\n----\n\nRPKI:\n\nFrom December 2020, AWS will drop all routes deemed to be RPKI invalid on incoming eBGP sessions.", "created": "2007-12-20T16:39:54Z", "org_id": 1520, "policy_url": "https://aws.amazon.com/peering/policy", "info_never_via_route_servers": false, "poc_updated": "2020-12-01T12:29:55Z", "info_type": "enterprise", "policy_contracts": "Not Required", "info_prefixes6": 2000, "aka": "Amazon Web Services", "info_prefixes4": 5000, "info_ipv6": true, "irr_as_set": "AS-AMAZON", "pop_list": [{"city": "Ashburn", "country": "US", "state": "VA", "org_name": "Equinix, Inc.", "isp_id_in_peering_db": 1, "location": [39.02, -77.46], "port_capacity": 401000, "isp_type_in_peering_db": "fac", "internet_penetration_percentage": 0.852}, {"city": "San Jose", "country": "US", "state": "CA", "org_name": "Equinix, Inc.", "isp_id_in_peering_db": 5, "location": [37.24, -121.78], "port_capacity": 401000, "isp_type_in_peering_db": "ix", "internet_penetration_percentage": 0.838}, {"city": "Palo Alto", "country": "US", "state": "CA", "org_name": "Equinix, Inc.", "isp_id_in_peering_db": 7, "location": [37.45, -122.16], "port_capacity": 121000, "isp_type_in_peering_db": "ix", "internet_penetration_percentage": 0.838}, {"city": "Secaucus", "country": "US", "state": "NJ", "org_name": "Equinix, Inc.", "isp_id_in_peering_db": 36, "location": [40.78, -74.07], "port_capacity": 1000, "isp_type_in_peering_db": "fac", "internet_penetration_percentage": 0.8240000000000001}, {"city": "New York", "country": "US", "state": "NY", "org_name": "Equinix, Inc.", "isp_id_in_peering_db": 38, "location": [40.74, -74.0], "port_capacity": 122000, "isp_type_in_peering_db": "fac", "internet_penetration_percentage": 0.802}, {"city": "McAllen", "country": "US", "state": "TX", "org_name": "MDC (McAllen Data Center)", "isp_id_in_peering_db": 2036, "location": [26.2, -98.23], "port_capacity": 10000, "isp_type_in_peering_db": "ix", "internet_penetration_percentage": 0.8170000000000001}, {"city": "Columbus", "country": "US", "state": "OH", "org_name": "Cologix, Inc.", "isp_id_in_peering_db": 2377, "location": [40.12, -83.0], "port_capacity": 1000, "isp_type_in_peering_db": "fac", "internet_penetration_percentage": 0.794}, {"city": "Dallas", "country": "US", "state": "TX", "org_name": "DE-CIX Management GmbH", "isp_id_in_peering_db": 1249, "location": [32.79, -96.79], "port_capacity": 20000, "isp_type_in_peering_db": "ix", "internet_penetration_percentage": 0.8170000000000001}, {"city": "Salt Lake City", "country": "US", "state": "UT", "org_name": "EdgeConneX", "isp_id_in_peering_db": 2077, "location": [40.72, -111.98], "port_capacity": 1000, "isp_type_in_peering_db": "fac", "internet_penetration_percentage": 0.877}, {"city": "Hillsboro", "country": "US", "state": "OR", "org_name": "EdgeConneX", "isp_id_in_peering_db": 1922, "location": [45.55, -122.91], "port_capacity": 1000, "isp_type_in_peering_db": "fac", "internet_penetration_percentage": 0.8740000000000001}, {"city": "Miami", "country": "US", "state": "FL", "org_name": "Community IX Holdings", "isp_id_in_peering_db": 954, "location": [25.78, -80.19], "port_capacity": 401000, "isp_type_in_peering_db": "ix", "internet_penetration_percentage": 0.8420000000000001}, {"city": "Tempe", "country": "US", "state": "AZ", "org_name": "EdgeConneX", "isp_id_in_peering_db": 1917, "location": [33.4, -111.97], "port_capacity": 1000, "isp_type_in_peering_db": "fac", "internet_penetration_percentage": 0.8390000000000001}, {"city": "Houston", "country": "US", "state": "TX", "org_name": "CyrusOne", "isp_id_in_peering_db": 1476, "location": [29.84, -95.56], "port_capacity": 1000, "isp_type_in_peering_db": "fac", "internet_penetration_percentage": 0.8170000000000001}, {"city": "Phoenix", "country": "US", "state": "AZ", "org_name": "Ninja-IX Corporation", "isp_id_in_peering_db": 662, "location": [33.45, -112.07], "port_capacity": 10000, "isp_type_in_peering_db": "ix", "internet_penetration_percentage": 0.8390000000000001}, {"city": "Minneapolis", "country": "US", "state": "MN", "org_name": "Midwest Internet Cooperative Exchange LLC", "isp_id_in_peering_db": 446, "location": [44.97, -93.25], "port_capacity": 201000, "isp_type_in_peering_db": "ix", "internet_penetration_percentage": 0.856}, {"city": "New York", "country": "US", "state": "NY", "org_name": "CoreSite LLC", "isp_id_in_peering_db": 670, "location": [40.72, -74.0], "port_capacity": 1000, "isp_type_in_peering_db": "fac", "internet_penetration_percentage": 0.802}, {"city": "Dallas", "country": "US", "state": "TX", "org_name": "Equinix, Inc.", "isp_id_in_peering_db": 69, "location": [32.8, -96.82], "port_capacity": 221000, "isp_type_in_peering_db": "fac", "internet_penetration_percentage": 0.8170000000000001}, {"city": "New York", "country": "US", "state": "NY", "org_name": "Digital Realty", "isp_id_in_peering_db": 325, "location": [40.72, -74.01], "port_capacity": 1000000, "isp_type_in_peering_db": "ix", "internet_penetration_percentage": 0.802}, {"city": "Seattle", "country": "US", "state": "WA", "org_name": "The Westin Building", "isp_id_in_peering_db": 71, "location": [47.61, -122.34], "port_capacity": 451000, "isp_type_in_peering_db": "fac", "internet_penetration_percentage": 0.885}, {"city": "Chicago", "country": "US", "state": "IL", "org_name": "United IX", "isp_id_in_peering_db": 239, "location": [41.85, -87.62], "port_capacity": 411000, "isp_type_in_peering_db": "ix", "internet_penetration_percentage": 0.865}, {"city": "Chicago", "country": "US", "state": "IL", "org_name": "CoreSite LLC", "isp_id_in_peering_db": 440, "location": [41.88, -87.63], "port_capacity": 101000, "isp_type_in_peering_db": "fac", "internet_penetration_percentage": 0.865}, {"city": "Vienna", "country": "US", "state": "VA", "org_name": "Equinix, Inc.", "isp_id_in_peering_db": 88, "location": [38.91, -77.22], "port_capacity": 1000, "isp_type_in_peering_db": "fac", "internet_penetration_percentage": 0.852}, {"city": "Seattle", "country": "US", "state": "WA", "org_name": "Hines", "isp_id_in_peering_db": 410, "location": [47.62, -122.35], "port_capacity": 1000, "isp_type_in_peering_db": "fac", "internet_penetration_percentage": 0.885}, {"city": "Denver", "country": "US", "state": "CO", "org_name": "CoreSite LLC", "isp_id_in_peering_db": 389, "location": [39.75, -105.0], "port_capacity": 102000, "isp_type_in_peering_db": "fac", "internet_penetration_percentage": 0.795}, {"city": "Atlanta", "country": "US", "state": "GA", "org_name": "Digital Realty", "isp_id_in_peering_db": 125, "location": [33.76, -84.39], "port_capacity": 201000, "isp_type_in_peering_db": "fac", "internet_penetration_percentage": 0.847}, {"city": "San Francisco", "country": "US", "state": "CA", "org_name": "SFMIX", "isp_id_in_peering_db": 155, "location": [37.72, -122.4], "port_capacity": 30000, "isp_type_in_peering_db": "ix", "internet_penetration_percentage": 0.838}, {"city": "Newark", "country": "US", "state": "NJ", "org_name": "Tishman Real Estate Services", "isp_id_in_peering_db": 350, "location": [40.74, -74.17], "port_capacity": 2000, "isp_type_in_peering_db": "fac", "internet_penetration_percentage": 0.8240000000000001}, {"city": "Los Angeles", "country": "US", "state": "CA", "org_name": "CoreSite LLC", "isp_id_in_peering_db": 142, "location": [34.05, -118.26], "port_capacity": 302000, "isp_type_in_peering_db": "ix", "internet_penetration_percentage": 0.838}, {"city": "Portland", "country": "US", "state": "OR", "org_name": "Alco Properties", "isp_id_in_peering_db": 275, "location": [45.52, -122.68], "port_capacity": 401000, "isp_type_in_peering_db": "fac", "internet_penetration_percentage": 0.8740000000000001}, {"city": "Boston", "country": "US", "state": "MA", "org_name": "Markley Group, LLC", "isp_id_in_peering_db": 219, "location": [42.35, -71.06], "port_capacity": 41000, "isp_type_in_peering_db": "fac", "internet_penetration_percentage": 0.784}, {"city": "Philadelphia", "country": "US", "state": "PA", "org_name": "Equinix, Inc.", "isp_id_in_peering_db": 146, "location": [39.96, -75.16], "port_capacity": 41000, "isp_type_in_peering_db": "fac", "internet_penetration_percentage": 0.782}], "prefixes": 5142, "total_prefixes_in_globe": 8388478, "address_space": 53846528, "total_addresses_in_globe": 22264797636, "neighbor": 343}