{"status": "ok", "looking_glass": "", "route_server": "", "netixlan_updated": "2020-05-27T18:19:44Z", "info_ratio": "Not Disclosed", "id": "14220", "policy_ratio": false, "info_unicast": true, "policy_general": "Open", "website": "https://www.beanfield.com", "allow_ixp_update": false, "updated": "2020-10-05T17:11:08Z", "netfac_updated": "2020-05-27T18:12:40Z", "info_traffic": "", "info_multicast": false, "asn": 21548, "policy_locations": "Not Required", "name": "Aptum Fibre (Montreal)", "info_scope": "Regional", "notes": "***AS21548 has been acquired by Beanfield (AS21949)*** and will cease direct peering by October 2020. All prefixes announced by AS21548 will be reachable via Beanfield AS21949.\n\nPlease see the Beanfield AS21949 PeeringDB entry for additional information, or contact us at peering at beanfield dot com.", "created": "2017-08-07T14:24:40Z", "org_id": 3667, "policy_url": "", "info_never_via_route_servers": false, "poc_updated": "2020-05-27T18:11:20Z", "info_type": "transit", "policy_contracts": "Not Required", "info_prefixes6": 10, "aka": "Aptum Fibre (Montreal), Cogeco Peer1 Montreal", "info_prefixes4": 200, "info_ipv6": true, "irr_as_set": "", "pop_list": [{"city": "Ashburn", "country": "US", "state": "VA", "org_name": "Equinix, Inc.", "isp_id_in_peering_db": 1, "location": [39.02, -77.46], "port_capacity": 100000, "isp_type_in_peering_db": "ix", "internet_penetration_percentage": 0.852}, {"city": "Chicago", "country": "US", "state": "IL", "org_name": "Equinix, Inc.", "isp_id_in_peering_db": 2, "location": [41.85, -87.62], "port_capacity": 101000, "isp_type_in_peering_db": "ix", "internet_penetration_percentage": 0.865}, {"city": "Seattle", "country": "US", "state": "WA", "org_name": "Equinix, Inc.", "isp_id_in_peering_db": 86, "location": [47.61, -122.34], "port_capacity": 22000, "isp_type_in_peering_db": "fac", "internet_penetration_percentage": 0.885}, {"city": "Columbus", "country": "US", "state": "OH", "org_name": "Cologix, Inc.", "isp_id_in_peering_db": 3313, "location": [40.12, -83.0], "port_capacity": 1000, "isp_type_in_peering_db": "fac", "internet_penetration_percentage": 0.794}, {"city": "Reston", "country": "US", "state": "VA", "org_name": "CoreSite LLC", "isp_id_in_peering_db": 668, "location": [38.95, -77.36], "port_capacity": 1000, "isp_type_in_peering_db": "fac", "internet_penetration_percentage": 0.852}, {"city": "New York", "country": "US", "state": "NY", "org_name": "Digital Realty", "isp_id_in_peering_db": 325, "location": [40.72, -74.01], "port_capacity": 501000, "isp_type_in_peering_db": "ix", "internet_penetration_percentage": 0.802}], "prefixes": 72, "total_prefixes_in_globe": 8388478, "address_space": 50432, "total_addresses_in_globe": 22264797636, "neighbor": 18}