{"status": "ok", "looking_glass": "", "route_server": "", "netixlan_updated": "2021-01-31T00:02:45Z", "info_ratio": "Heavy Outbound", "id": "4150", "policy_ratio": false, "info_unicast": true, "policy_general": "Selective", "website": "http://www.gnax.net", "allow_ixp_update": false, "updated": "2019-03-11T21:54:49Z", "netfac_updated": null, "info_traffic": "", "info_multicast": false, "asn": 3595, "policy_locations": "Not Required", "name": "zColo Atlanta (deprecated ASN)", "info_scope": "North America", "notes": "", "created": "2011-07-27T01:33:26Z", "org_id": 6935, "policy_url": "", "info_never_via_route_servers": false, "poc_updated": "2016-03-14T20:40:27Z", "info_type": "content", "policy_contracts": "Not Required", "info_prefixes6": 15, "aka": "", "info_prefixes4": 300, "info_ipv6": true, "irr_as_set": "as-gnax-3595", "pop_list": [{"city": "Ashburn", "country": "US", "state": "VA", "org_name": "Equinix, Inc.", "isp_id_in_peering_db": 1, "location": [39.02, -77.46], "port_capacity": 101000, "isp_type_in_peering_db": "fac", "internet_penetration_percentage": 0.852}, {"city": "Palo Alto", "country": "US", "state": "CA", "org_name": "Equinix, Inc.", "isp_id_in_peering_db": 5, "location": [37.45, -122.16], "port_capacity": 1000, "isp_type_in_peering_db": "fac", "internet_penetration_percentage": 0.838}, {"city": "San Jose", "country": "US", "state": "CA", "org_name": "Equinix, Inc.", "isp_id_in_peering_db": 6, "location": [37.24, -121.78], "port_capacity": 1000, "isp_type_in_peering_db": "fac", "internet_penetration_percentage": 0.838}, {"city": "Chicago", "country": "US", "state": "IL", "org_name": "Equinix, Inc.", "isp_id_in_peering_db": 7, "location": [41.85, -87.62], "port_capacity": 101000, "isp_type_in_peering_db": "fac", "internet_penetration_percentage": 0.865}, {"city": "Los Angeles", "country": "US", "state": "CA", "org_name": "Equinix, Inc.", "isp_id_in_peering_db": 8, "location": [34.05, -118.26], "port_capacity": 101000, "isp_type_in_peering_db": "fac", "internet_penetration_percentage": 0.838}, {"city": "Atlanta", "country": "US", "state": "GA", "org_name": "Zayo Group", "isp_id_in_peering_db": 3853, "location": [33.73, -84.43], "port_capacity": 1000, "isp_type_in_peering_db": "fac", "internet_penetration_percentage": 0.847}, {"city": "New York", "country": "US", "state": "NY", "org_name": "Digital Realty", "isp_id_in_peering_db": 16, "location": [40.74, -74.0], "port_capacity": 101000, "isp_type_in_peering_db": "fac", "internet_penetration_percentage": 0.802}, {"city": "Englewood", "country": "US", "state": "CO", "org_name": "Zayo Group", "isp_id_in_peering_db": 2977, "location": [39.56, -104.87], "port_capacity": 1000, "isp_type_in_peering_db": "fac", "internet_penetration_percentage": 0.795}, {"city": "Englewood", "country": "US", "state": "CO", "org_name": "Zayo Group", "isp_id_in_peering_db": 2198, "location": [39.58, -104.85], "port_capacity": 1000, "isp_type_in_peering_db": "fac", "internet_penetration_percentage": 0.795}, {"city": "Dallas", "country": "US", "state": "TX", "org_name": "Zayo Group", "isp_id_in_peering_db": 1738, "location": [32.84, -96.87], "port_capacity": 1000, "isp_type_in_peering_db": "fac", "internet_penetration_percentage": 0.8170000000000001}, {"city": "Dallas", "country": "US", "state": "TX", "org_name": "Equinix, Inc.", "isp_id_in_peering_db": 505, "location": [32.8, -96.82], "port_capacity": 103000, "isp_type_in_peering_db": "fac", "internet_penetration_percentage": 0.8170000000000001}, {"city": "Ashburn", "country": "US", "state": "VA", "org_name": "Zayo Group", "isp_id_in_peering_db": 1223, "location": [39.02, -77.48], "port_capacity": 1000, "isp_type_in_peering_db": "fac", "internet_penetration_percentage": 0.852}, {"city": "Wall", "country": "US", "state": "NJ", "org_name": "NJFX, LLC", "isp_id_in_peering_db": 5945, "location": [40.16, -74.05], "port_capacity": 1000, "isp_type_in_peering_db": "fac", "internet_penetration_percentage": 0.8240000000000001}, {"city": "Louisville", "country": "US", "state": "CO", "org_name": "Zayo Group", "isp_id_in_peering_db": 1049, "location": [39.96, -105.17], "port_capacity": 1000, "isp_type_in_peering_db": "fac", "internet_penetration_percentage": 0.795}, {"city": "Houston", "country": "US", "state": "TX", "org_name": "Netrality Data Centers", "isp_id_in_peering_db": 409, "location": [29.75, -95.37], "port_capacity": 1000, "isp_type_in_peering_db": "fac", "internet_penetration_percentage": 0.8170000000000001}, {"city": "El Segundo", "country": "US", "state": "CA", "org_name": "Equinix, Inc.", "isp_id_in_peering_db": 333, "location": [33.92, -118.38], "port_capacity": 1000, "isp_type_in_peering_db": "fac", "internet_penetration_percentage": 0.838}, {"city": "Dallas", "country": "US", "state": "TX", "org_name": "DE-CIX Management GmbH", "isp_id_in_peering_db": 1249, "location": [32.79, -96.79], "port_capacity": 10000, "isp_type_in_peering_db": "ix", "internet_penetration_percentage": 0.8170000000000001}, {"city": "Miami", "country": "US", "state": "FL", "org_name": "Community IX Holdings", "isp_id_in_peering_db": 954, "location": [25.78, -80.19], "port_capacity": 41000, "isp_type_in_peering_db": "ix", "internet_penetration_percentage": 0.8420000000000001}, {"city": "Atlanta", "country": "US", "state": "GA", "org_name": "Digital Realty", "isp_id_in_peering_db": 125, "location": [33.76, -84.39], "port_capacity": 131000, "isp_type_in_peering_db": "fac", "internet_penetration_percentage": 0.847}, {"city": "San Jose", "country": "US", "state": "CA", "org_name": "Amsterdam Internet Exchange BV", "isp_id_in_peering_db": 935, "location": [37.33, -121.89], "port_capacity": 1000, "isp_type_in_peering_db": "ix", "internet_penetration_percentage": 0.838}, {"city": "New York", "country": "US", "state": "NY", "org_name": "DE-CIX Management GmbH", "isp_id_in_peering_db": 804, "location": [40.72, -74.01], "port_capacity": 20000, "isp_type_in_peering_db": "ix", "internet_penetration_percentage": 0.802}, {"city": "Minneapolis", "country": "US", "state": "MN", "org_name": "Midwest Internet Cooperative Exchange LLC", "isp_id_in_peering_db": 446, "location": [44.97, -93.25], "port_capacity": 10000, "isp_type_in_peering_db": "ix", "internet_penetration_percentage": 0.856}, {"city": "Seattle", "country": "US", "state": "WA", "org_name": "The Westin Building", "isp_id_in_peering_db": 71, "location": [47.61, -122.34], "port_capacity": 51000, "isp_type_in_peering_db": "fac", "internet_penetration_percentage": 0.885}, {"city": "Phoenix", "country": "US", "state": "AZ", "org_name": "Digital Realty", "isp_id_in_peering_db": 256, "location": [33.45, -112.07], "port_capacity": 20000, "isp_type_in_peering_db": "ix", "internet_penetration_percentage": 0.8390000000000001}], "prefixes": 9, "total_prefixes_in_globe": 8388478, "address_space": 4608, "total_addresses_in_globe": 22264797636, "neighbor": 1}