{"status": "ok", "looking_glass": "", "route_server": "", "netixlan_updated": "2021-01-11T17:39:34Z", "info_ratio": "Mostly Inbound", "id": "10741", "policy_ratio": false, "info_unicast": true, "policy_general": "Open", "website": "https://www.starry.com", "allow_ixp_update": false, "updated": "2020-04-24T16:00:07Z", "netfac_updated": null, "info_traffic": "", "info_multicast": false, "asn": 395354, "policy_locations": "Not Required", "name": "Starry", "info_scope": "North America", "notes": "", "created": "2016-07-14T21:16:20Z", "org_id": 14592, "policy_url": "", "info_never_via_route_servers": false, "poc_updated": "2016-07-15T17:46:39Z", "info_type": "access", "policy_contracts": "Not Required", "info_prefixes6": 15, "aka": "", "info_prefixes4": 100, "info_ipv6": true, "irr_as_set": "", "pop_list": [{"city": "Ashburn", "country": "US", "state": "VA", "org_name": "Equinix, Inc.", "isp_id_in_peering_db": 1, "location": [39.02, -77.46], "port_capacity": 10000, "isp_type_in_peering_db": "ix", "internet_penetration_percentage": 0.852}, {"city": "Los Angeles", "country": "US", "state": "CA", "org_name": "CoreSite LLC", "isp_id_in_peering_db": 142, "location": [34.05, -118.26], "port_capacity": 10000, "isp_type_in_peering_db": "ix", "internet_penetration_percentage": 0.838}, {"city": "Denver", "country": "US", "state": "CO", "org_name": "CoreSite LLC", "isp_id_in_peering_db": 254, "location": [39.75, -105.0], "port_capacity": 10000, "isp_type_in_peering_db": "ix", "internet_penetration_percentage": 0.795}, {"city": "New York", "country": "US", "state": "NY", "org_name": "DE-CIX Management GmbH", "isp_id_in_peering_db": 804, "location": [40.72, -74.01], "port_capacity": 10000, "isp_type_in_peering_db": "ix", "internet_penetration_percentage": 0.802}], "prefixes": 48, "total_prefixes_in_globe": 8388478, "address_space": 37120, "total_addresses_in_globe": 22264797636, "neighbor": 45}