{"status": "ok", "looking_glass": "", "route_server": "", "netixlan_updated": "2021-01-31T00:03:19Z", "info_ratio": "Mostly Inbound", "id": "9833", "policy_ratio": false, "info_unicast": true, "policy_general": "Open", "website": "", "allow_ixp_update": false, "updated": "2018-05-15T04:15:58Z", "netfac_updated": "2019-10-22T16:15:03Z", "info_traffic": "", "info_multicast": false, "asn": 64208, "policy_locations": "Not Required", "name": "Virtustream", "info_scope": "North America", "notes": "", "created": "2016-03-22T01:20:03Z", "org_id": 7016, "policy_url": "", "info_never_via_route_servers": false, "poc_updated": "2020-01-22T04:24:13Z", "info_type": "transit", "policy_contracts": "Not Required", "info_prefixes6": 2, "aka": "EMC, Dell", "info_prefixes4": 50, "info_ipv6": true, "irr_as_set": "AS-VIRTUSTREAM", "pop_list": [{"city": "Ashburn", "country": "US", "state": "VA", "org_name": "Equinix, Inc.", "isp_id_in_peering_db": 1, "location": [39.02, -77.46], "port_capacity": 11000, "isp_type_in_peering_db": "fac", "internet_penetration_percentage": 0.852}, {"city": "Chicago", "country": "US", "state": "IL", "org_name": "Equinix, Inc.", "isp_id_in_peering_db": 2, "location": [41.85, -87.62], "port_capacity": 10000, "isp_type_in_peering_db": "ix", "internet_penetration_percentage": 0.865}, {"city": "San Jose", "country": "US", "state": "CA", "org_name": "Equinix, Inc.", "isp_id_in_peering_db": 6, "location": [37.24, -121.78], "port_capacity": 11000, "isp_type_in_peering_db": "fac", "internet_penetration_percentage": 0.838}, {"city": "Palo Alto", "country": "US", "state": "CA", "org_name": "Equinix, Inc.", "isp_id_in_peering_db": 7, "location": [37.45, -122.16], "port_capacity": 11000, "isp_type_in_peering_db": "ix", "internet_penetration_percentage": 0.838}, {"city": "Chicago", "country": "US", "state": "IL", "org_name": "CoreSite LLC", "isp_id_in_peering_db": 440, "location": [41.88, -87.63], "port_capacity": 1000, "isp_type_in_peering_db": "fac", "internet_penetration_percentage": 0.865}, {"city": "Las Vegas", "country": "US", "state": "NV", "org_name": "Switch, Ltd.", "isp_id_in_peering_db": 770, "location": [36.06, -115.21], "port_capacity": 1000, "isp_type_in_peering_db": "fac", "internet_penetration_percentage": 0.875}, {"city": "Elk Grove Village", "country": "US", "state": "IL", "org_name": "Equinix, Inc.", "isp_id_in_peering_db": 968, "location": [42.0, -87.95], "port_capacity": 1000, "isp_type_in_peering_db": "fac", "internet_penetration_percentage": 0.865}, {"city": "Carrollton", "country": "US", "state": "TX", "org_name": "CyrusOne", "isp_id_in_peering_db": 1481, "location": [32.99, -96.93], "port_capacity": 1000, "isp_type_in_peering_db": "fac", "internet_penetration_percentage": 0.8170000000000001}, {"city": "Santa Clara", "country": "US", "state": "CA", "org_name": "CoreSite LLC", "isp_id_in_peering_db": 1619, "location": [37.38, -121.97], "port_capacity": 1000, "isp_type_in_peering_db": "fac", "internet_penetration_percentage": 0.838}, {"city": "Sterling", "country": "US", "state": "VA", "org_name": "Cyxtera Technologies, Inc.", "isp_id_in_peering_db": 2615, "location": [39.03, -77.41], "port_capacity": 1000, "isp_type_in_peering_db": "fac", "internet_penetration_percentage": 0.852}, {"city": "Manassas", "country": "US", "state": "VA", "org_name": "Iron Mountain Data Centers", "isp_id_in_peering_db": 5373, "location": [38.78, -77.55], "port_capacity": 1000, "isp_type_in_peering_db": "fac", "internet_penetration_percentage": 0.852}], "prefixes": 27, "total_prefixes_in_globe": 8388478, "address_space": 71936, "total_addresses_in_globe": 22264797636, "neighbor": 33}